pyleft/__init__.py
pyleft/__main__.py
pyleft/api.py
pyleft/console.py
pyleft/models.py
pyleft/path_utils.py
pyleft/printing.py
pyleft/settings.py
pyleft-1.2.2.dist-info/LICENSE
pyleft-1.2.2.dist-info/METADATA
pyleft-1.2.2.dist-info/WHEEL
pyleft-1.2.2.dist-info/entry_points.txt
pyleft-1.2.2.dist-info/RECORD
