Metadata-Version: 2.1
Name: pyleft
Version: 1.2.2
Summary: Python type annotation existence checker
Home-page: https://github.com/NathanVaughn/pyleft
License: MIT
Author: Nathan Vaughn
Author-email: nvaughn51@gmail.com
Requires-Python: >=3.7,<4.0
Classifier: Intended Audience :: Developers
Classifier: License :: OSI Approved :: MIT License
Classifier: Programming Language :: Python :: 3
Classifier: Programming Language :: Python :: 3.7
Classifier: Programming Language :: Python :: 3.8
Classifier: Programming Language :: Python :: 3.9
Classifier: Programming Language :: Python :: 3.10
Classifier: Programming Language :: Python :: 3.11
Classifier: Topic :: Software Development :: Libraries :: Python Modules
Classifier: Topic :: Software Development :: Quality Assurance
Requires-Dist: pathspec (>=0.9.0)
Requires-Dist: tomli (>=1.1.0) ; python_version < "3.11"
Project-URL: Issues, https://github.com/NathanVaughn/pyleft/issues
Project-URL: Repository, https://github.com/NathanVaughn/pyleft.git
